coaction/__init__.py
coaction/create.py
coaction/run.py
coaction/_templates/_agent.txt
coaction/_templates/_project_config.txt
coaction/agents/__init__.py
coaction/agents/agent.py
coaction/agents/fictitious_play/__init__.py
coaction/agents/fictitious_play/async_fp.py
coaction/agents/fictitious_play/async_sfp.py
coaction/agents/fictitious_play/model_free_fp.py
coaction/agents/fictitious_play/model_free_sfp.py
coaction/agents/fictitious_play/sync_fp.py
coaction/agents/fictitious_play/sync_sfp.py
coaction/agents/fictitious_play/utils.py
coaction/agents/ind_q/__init__.py
coaction/agents/ind_q/ind_q.py
coaction/agents/ind_q/utils.py
coaction/experiments/__init__.py
coaction/experiments/config.py
coaction/experiments/episode.py
coaction/experiments/experiment.py
coaction/experiments/multiprocessing.py
coaction/experiments/project.py
coaction/games/__init__.py
coaction/games/game.py
coaction/loggers/__init__.py
coaction/loggers/agent.py
coaction/loggers/game.py
coaction/loggers/loader.py
coaction/loggers/logger.py
coaction/loggers/progress.py
coaction/utils/__init__.py
coaction/utils/games.py
coaction/utils/io.py
coaction/utils/math.py
coaction/utils/modules.py
coaction/utils/paths.py
coaction/utils/progress.py
coaction/utils/time.py
coaction-0.0.9.dist-info/LICENSE
coaction-0.0.9.dist-info/METADATA
coaction-0.0.9.dist-info/WHEEL
coaction-0.0.9.dist-info/top_level.txt
coaction-0.0.9.dist-info/RECORD
