Metadata-Version: 2.1
Name: coaction
Version: 0.0.9
Summary: A library for multi-agent learning that aims to accelarate the research.
Author-email: Yiğit Yalın <yigityalin@outlook.com>
Project-URL: Homepage, https://github.com/yigityalin/coaction
Project-URL: Bug Tracker, https://github.com/yigityalin/coaction/issues
Classifier: Programming Language :: Python :: 3
Classifier: License :: OSI Approved :: MIT License
Classifier: Operating System :: OS Independent
Requires-Python: >=3.11.4
License-File: LICENSE
Requires-Dist: numpy >=1.25.2
Requires-Dist: scipy >=1.11.2
